pure_scraper/__init__.py
pure_scraper/cache.py
pure_scraper/cli.py
pure_scraper/config.py
pure_scraper/fetcher.py
pure_scraper/parser.py
pure_scraper/utils.py
pure_scraper-2.0.0.dist-info/METADATA
pure_scraper-2.0.0.dist-info/WHEEL
pure_scraper-2.0.0.dist-info/entry_points.txt
pure_scraper-2.0.0.dist-info/top_level.txt
pure_scraper-2.0.0.dist-info/RECORD
