Metadata-Version: 2.4
Name: pure-scraper
Version: 2.0.0
Summary: A pure Python HTML parser and scraper (BeautifulSoup alternative)
Author: Rohit
Author-email: Rohit <rohitkumar@devexhub.in>
License-Expression: MIT
Requires-Python: >=3.7
Requires-Dist: lxml
Dynamic: author
Dynamic: description
Dynamic: description-content-type
Dynamic: requires-python
